{
  "main": {
    "id": "25c40447076f46c3",
    "type": "split",
    "children": [
      {
        "id": "b2f571491990539b",
        "type": "tabs",
        "children": [
          {
            "id": "c0d15a1cd1904cf6",
            "type": "leaf",
            "state": {
              "type": "markdown",
              "state": {
                "file": "README.md",
                "mode": "source",
                "source": false
              }
            }
          }
        ]
      }
    ],
    "direction": "vertical"
  },
  "left": {
    "id": "ad80e82fb0cbc22c",
    "type": "split",
    "children": [
      {
        "id": "25547694f7f4d057",
        "type": "tabs",
        "children": [
          {
            "id": "8a3e3ecf117c98b1",
            "type": "leaf",
            "state": {
              "type": "file-explorer",
              "state": {
                "sortOrder": "alphabetical"
              }
            }
          },
          {
            "id": "d8d1f644eb79d570",
            "type": "leaf",
            "state": {
              "type": "search",
              "state": {
                "query": "tag:#event",
                "matchingCase": false,
                "explainSearch": false,
                "collapseAll": false,
                "extraContext": false,
                "sortOrder": "alphabetical"
              }
            }
          },
          {
            "id": "08fcad7b3eb30225",
            "type": "leaf",
            "state": {
              "type": "bookmarks",
              "state": {}
            }
          }
        ]
      }
    ],
    "direction": "horizontal",
    "width": 300
  },
  "right": {
    "id": "0a8aec1bdf1c363d",
    "type": "split",
    "children": [
      {
        "id": "b1c887c7b77cfe08",
        "type": "tabs",
        "children": [
          {
            "id": "8ff4936daae60879",
            "type": "leaf",
            "state": {
              "type": "backlink",
              "state": {
                "file": "README.md",
                "collapseAll": false,
                "extraContext": false,
                "sortOrder": "alphabetical",
                "showSearch": false,
                "searchQuery": "",
                "backlinkCollapsed": false,
                "unlinkedCollapsed": true
              }
            }
          },
          {
            "id": "a4cdefc34a20f9c1",
            "type": "leaf",
            "state": {
              "type": "outgoing-link",
              "state": {
                "file": "README.md",
                "linksCollapsed": false,
                "unlinkedCollapsed": true
              }
            }
          },
          {
            "id": "4ba087dbab4f1343",
            "type": "leaf",
            "state": {
              "type": "tag",
              "state": {
                "sortOrder": "frequency",
                "useHierarchy": false
              }
            }
          },
          {
            "id": "1b8bfdfe7a25f126",
            "type": "leaf",
            "state": {
              "type": "outline",
              "state": {
                "file": "README.md"
              }
            }
          }
        ],
        "currentTab": 2
      }
    ],
    "direction": "horizontal",
    "width": 300
  },
  "left-ribbon": {
    "hiddenItems": {
      "switcher:Open quick switcher": false,
      "graph:Open graph view": false,
      "canvas:Create new canvas": false,
      "daily-notes:Open today's daily note": false,
      "templates:Insert template": false,
      "command-palette:Open command palette": false
    }
  },
  "active": "c0d15a1cd1904cf6",
  "lastOpenFiles": [
    "Permanent notes/Can insert more than 1 template in an Obsidian note.md",
    "Permanent notes/Turn off auto display of titles in Obsidian settings.md",
    "Notes/2021.05.06 400 Cellular to Washington Lake Park.md",
    "Notes/2021.05.07 400 Cellular trip through Pine Barrens.md",
    "Notes/2021.05.17 Baltimore Harbor Tunnel to Annapolis to western Delaware round trip.md",
    "Notes/2021.05.24 Baltimore to Annapolis to western MD.md",
    "Notes/2021.05.26 AC Expressway.md",
    "Notes/2021.05.27 Baltimore to Annapolis to western MD.md",
    "Notes/2021.05.28 AC Expressway.md",
    "Notes/2021.05.28 White Castle.md",
    "Notes/2021.06.01 Various South NJ.md",
    "Notes/2021.06.02 Exton.md",
    "Notes/2021.06.07 Cape May Lewes ferry.md",
    "Notes/2021.06.25 AC Expressway.md",
    "Notes/2021.07.30 Sensaphone to Baltimore-Annapolis-Chesapeake Bay.md",
    "Notes/2021.07.28 Sensaphone to Baltimore-Annapolis-Chesapeake Bay.md",
    "Notes/2021.07.23 Sensaphone to Baltimore-Annapolis-Chesapeake Bay.md",
    "Notes/2021.06.27 AC Expressway.md",
    "README.md",
    "Notes/2021.08.16 AC Expressway.md",
    "Notes/2021.12.13 Baltimore-Annapolis-Chesapeake Bay loop.md",
    "Notes/2023.05.24 400 Cellular around Sensaphone.md",
    "Notes/2023.05.25 RGM to Annapolis.md",
    "Notes/2023.05.30 NAWCC to Annapolis.md",
    "Notes/2023.06.05 Home to A expressway rest stop.md",
    "Notes/2023.06.06 Lancaster County to Baltimore to Annapolis.md",
    "Notes",
    "Permanent notes",
    "Literature notes",
    "Fleeting notes",
    "Templates"
  ]
}